deepbay/DeepFeedForward.py
deepbay/DenseBlock.py
deepbay/GeneralizedMatrixFactorizer.py
deepbay/NeuralCollaborativeFilter.py
deepbay/__init__.py
tests/__init__.py
tests/test_dense_block.py
deepbay-0.8.3.dist-info/LICENSE
deepbay-0.8.3.dist-info/METADATA
deepbay-0.8.3.dist-info/WHEEL
deepbay-0.8.3.dist-info/top_level.txt
deepbay-0.8.3.dist-info/RECORD
