Metadata-Version: 2.1
Name: deepbay
Version: 0.8.3
Summary: Tensorflow/Keras Plug-N-Play Deep Learning Models Compilation
Home-page: https://github.com/ElPapi42/DeepBay
Author: Whitman Bohorquez
Author-email: whitman-2@hotmail.com
License: UNKNOWN
Download-URL: https://github.com/ElPapi42/DeepBay/archive/v0.8.3.tar.gz
Keywords: Keras,Model,Plug And Play,Tensorflow
Platform: UNKNOWN
Classifier: Programming Language :: Python :: 3
Classifier: License :: OSI Approved :: MIT License
Classifier: Operating System :: OS Independent
Requires-Python: >=3.6
